_swigPageXML.cpython-310-x86_64-linux-gnu.so
pagexml_slim-2022.4.12.dist-info/RECORD
pagexml_slim-2022.4.12.dist-info/METADATA
pagexml_slim-2022.4.12.dist-info/top_level.txt
pagexml_slim-2022.4.12.dist-info/WHEEL
pagexml/__init__.py
pagexml/swigPageXML.py
pagexml/xsd/pagecontent_omnius.xsd
pagexml/xsd/pagecontent_searchink.xsd
pagexml_tests/__init__.py
pagexml_tests/groups_tests.py
pagexml_tests/basic_tests.py
pagexml_tests/ordering_tests.py
pagexml_tests/__main__.py
pagexml_tests/textequiv_tests.py
pagexml_tests/examples/lorem.xml
pagexml_tests/examples/lorem_tess.xml
pagexml_tests/examples/lorem.png
