Metadata-Version: 2.1
Name: pagexml-slim
Version: 2022.4.12
Summary: Wrapper for the PageXML C++ library to ease handling of Page XML files within python.
Home-page: https://github.com/omni-us/pagexml
Author: Mauricio Villegas
Author-email: mauricio@omnius.com
License: MIT
Project-URL: Documentation, https://omni-us.github.io/pagexml/py-pagexml/
Project-URL: GitHub, https://github.com/omni-us/pagexml
Project-URL: PyPI, https://pypi.org/project/pagexml-slim/
Platform: UNKNOWN
Requires-Python: >=3.6
Provides-Extra: all
Requires-Dist: opencv-python (>=3.2.0) ; extra == 'all'
Provides-Extra: dev
Requires-Dist: opencv-python (>=3.2.0) ; extra == 'dev'
Requires-Dist: coverage (>=4.5.1) ; extra == 'dev'
Requires-Dist: pylint (>=1.8.3) ; extra == 'dev'
Requires-Dist: Sphinx (>=1.7.9) ; extra == 'dev'
Requires-Dist: sphinx-rtd-theme (>=0.4.3) ; extra == 'dev'
Requires-Dist: autodocsumm (>=0.1.10) ; extra == 'dev'
Requires-Dist: pkgconfig (>=1.1.0) ; extra == 'dev'
Provides-Extra: test
Requires-Dist: coverage (>=4.5.1) ; extra == 'test'
